<DynamicBoundingBoxes>
  <BoundingBox actorId="2879" class="Motorcycle">
    <on_screen on_screen="false" />
    <center x="-1.186737060546875" y="-0.37960338592529297" z="0.5750411748886108" />
    <verts>
      <v0 x="188.2959442138672" y="114.19574737548828" z="2.059074640274048" />
      <v1 x="188.36744689941406" y="114.16292572021484" z="3.1630992889404297" />
      <v2 x="188.2959442138672" y="114.19574737548828" z="2.059074640274048" />
      <v3 x="188.36744689941406" y="114.16292572021484" z="3.1630992889404297" />
      <v4 x="188.2959442138672" y="114.19574737548828" z="2.059074640274048" />
      <v5 x="188.36744689941406" y="114.16292572021484" z="3.1630992889404297" />
      <v6 x="188.2959442138672" y="114.19574737548828" z="2.059074640274048" />
      <v7 x="188.36744689941406" y="114.16292572021484" z="3.1630992889404297" />
    </verts>
    <shape x="0.0" y="0.0" z="1.1068246364593506" />
    <word_orientation pitch="-0.1627497375011444" roll="-0.029663076624274254" yaw="90.5488510131836" />
    <relative_orientation observation_angle="1.7758090818561292" pitch="-0.2443295121192932" roll="-0.11124285124242306" yaw="90.46727123856544" />
    <relative_center x="4.879605242539384" y="2.2494790770261215" z="14.90398394362137" />
    <Box2d xMax="829.1846115675222" xMin="825.6112567515795" yMax="459.118978533238" yMin="408.54652328498287" />
    <edge0 x1="825.6112567515795" x2="829.1846115675222" y1="459.118978533238" y2="408.54652328498287" />
    <edge1 x1="829.1846115675222" x2="829.1846115675222" y1="408.54652328498287" y2="408.54652328498287" />
    <edge2 x1="829.1846115675222" x2="825.6112567515795" y1="408.54652328498287" y2="459.118978533238" />
    <edge3 x1="825.6112567515795" x2="825.6112567515795" y1="459.118978533238" y2="459.118978533238" />
    <edge4 x1="825.6112567515795" x2="825.6112567515795" y1="459.118978533238" y2="459.118978533238" />
    <edge5 x1="825.6112567515795" x2="829.1846115675222" y1="459.118978533238" y2="408.54652328498287" />
    <edge6 x1="829.1846115675222" x2="829.1846115675222" y1="408.54652328498287" y2="408.54652328498287" />
    <edge7 x1="829.1846115675222" x2="829.1846115675222" y1="408.54652328498287" y2="408.54652328498287" />
    <edge8 x1="829.1846115675222" x2="825.6112567515795" y1="408.54652328498287" y2="459.118978533238" />
    <edge9 x1="825.6112567515795" x2="825.6112567515795" y1="459.118978533238" y2="459.118978533238" />
    <edge10 x1="825.6112567515795" x2="825.6112567515795" y1="459.118978533238" y2="459.118978533238" />
    <edge11 x1="829.1846115675222" x2="829.1846115675222" y1="408.54652328498287" y2="408.54652328498287" />
  </BoundingBox>
  <BoundingBox actorId="2803" class="TrafficSigns">
    <on_screen on_screen="false" />
    <center x="196.0500030517578" y="135.22999572753906" z="2.2300000190734863" />
    <verts>
      <v0 x="142.9710235595703" y="348.626953125" z="13.837052345275879" />
      <v1 x="143.0150909423828" y="348.6067199707031" z="14.51745891571045" />
      <v2 x="142.90155029296875" y="348.6571960449219" z="13.842451095581055" />
      <v3 x="142.94561767578125" y="348.636962890625" z="14.522857666015625" />
      <v4 x="143.24317932128906" y="349.25244140625" z="13.838024139404297" />
      <v5 x="143.28724670410156" y="349.2322082519531" z="14.518430709838867" />
      <v6 x="143.1737060546875" y="349.28265380859375" z="13.843422889709473" />
      <v7 x="143.2177734375" y="349.2624206542969" z="14.523829460144043" />
    </verts>
    <shape x="0.6821317672729492" y="0.07595250010490417" z="0.6821319460868835" />
    <word_orientation pitch="0.0" roll="0.0" yaw="0.0" />
    <relative_orientation observation_angle="1.5634051845273627" pitch="-0.0815797746181488" roll="-0.0815797746181488" yaw="-0.0815797746181488" />
    <relative_center x="0.9093095659924018" y="-0.06920472364112129" z="21.19473130193073" />
    <Box2d xMax="678.2478994175799" xMin="656.769575582833" yMax="368.9252961494057" yMin="347.0005155579925" />
    <edge0 x1="675.9805166057515" x2="677.4546008146586" y1="368.8862853669429" y2="348.17366081171036" />
    <edge1 x1="677.4546008146586" x2="678.2478994175799" y1="348.17366081171036" y2="348.28106098755933" />
    <edge2 x1="678.2478994175799" x2="676.7787192519235" y1="348.28106098755933" y2="368.9252961494057" />
    <edge3 x1="676.7787192519235" x2="675.9805166057515" y1="368.9252961494057" y2="368.8862853669429" />
    <edge4 x1="675.9805166057515" x2="656.769575582833" y1="368.8862853669429" y2="367.4483752564766" />
    <edge5 x1="656.769575582833" x2="658.2256977003103" y1="367.4483752564766" y2="347.0005155579925" />
    <edge6 x1="658.2256977003103" x2="677.4546008146586" y1="347.0005155579925" y2="348.17366081171036" />
    <edge7 x1="658.2256977003103" x2="659.0715746226472" y1="347.0005155579925" y2="347.1103719518879" />
    <edge8 x1="659.0715746226472" x2="657.620237911922" y1="347.1103719518879" y2="367.4915766816551" />
    <edge9 x1="657.620237911922" x2="656.769575582833" y1="367.4915766816551" y2="367.4483752564766" />
    <edge10 x1="657.620237911922" x2="676.7787192519235" y1="367.4915766816551" y2="368.9252961494057" />
    <edge11 x1="659.0715746226472" x2="678.2478994175799" y1="347.1103719518879" y2="348.28106098755933" />
  </BoundingBox>
</DynamicBoundingBoxes>
