<OccludedBoundingBoxes>
  <BoundingBox class="TrafficLight">
    <on_screen on_screen="true" />
    <center x="39.47570037841797" y="226.86941528320312" z="2.724909543991089" />
    <verts>
      </verts>
    <shape x="0.27717283368110657" y="0.45076170563697815" z="1.221373438835144" />
    <word_orientation pitch="0.0" yaw="179.99989318847656" roll="0.0" />
    <relative_orientation pitch="-0.03893207758665085" yaw="179.9609611108899" roll="-0.03893207758665085" />
    <Box2d xMin="-9783.496652530623" xMax="-8679.659353487696" yMin="239.52963296835398" yMax="521.823934453541" />
    <edge0 x1="-8738.288300433585" y1="521.823934453541" x2="-8736.947747875596" y2="268.8101179373814" />
    <edge1 x1="-8736.947747875596" y1="268.8101179373814" x2="-9781.851589303798" y2="239.53416245214058" />
    <edge2 x1="-9781.851589303798" y1="239.53416245214058" x2="-9783.496652530623" y2="519.8108306597522" />
    <edge3 x1="-9783.496652530623" y1="519.8108306597522" x2="-8738.288300433585" y2="521.823934453541" />
    <edge4 x1="-8738.288300433585" y1="521.823934453541" x2="-8680.99200323382" y2="521.8236468715488" />
    <edge5 x1="-8680.99200323382" y1="521.8236468715488" x2="-8679.659353487696" y2="268.80642328540023" />
    <edge6 x1="-8679.659353487696" y1="268.80642328540023" x2="-8736.947747875596" y2="268.8101179373814" />
    <edge7 x1="-8679.659353487696" y1="268.80642328540023" x2="-9718.405656726432" y2="239.52963296835398" />
    <edge8 x1="-9718.405656726432" y1="239.52963296835398" x2="-9720.041026872266" y2="519.8104820501848" />
    <edge9 x1="-9720.041026872266" y1="519.8104820501848" x2="-8680.99200323382" y2="521.8236468715488" />
    <edge10 x1="-9720.041026872266" y1="519.8104820501848" x2="-9783.496652530623" y2="519.8108306597522" />
    <edge11 x1="-9718.405656726432" y1="239.52963296835398" x2="-9781.851589303798" y2="239.53416245214058" />
  </BoundingBox>
</OccludedBoundingBoxes>
