<OccludedBoundingBoxes>
  <BoundingBox class="TrafficSigns">
    <on_screen on_screen="false" />
    <center x="196.0500030517578" y="135.22999572753906" z="2.2300000190734863" />
    <verts>
      </verts>
    <shape x="0.6821317672729492" y="0.07595250010490417" z="0.6821319460868835" />
    <word_orientation pitch="0.0" roll="0.0" yaw="0.0" />
    <relative_orientation observation_angle="0.9208003842373107" pitch="0.19482430815696716" roll="0.19482430815696716" yaw="0.19482430815696716" />
    <relative_center x="26.06778531295029" y="-0.32238513533401125" z="34.04982169627476" />
    <Box2d xMax="1135.6617498302542" xMin="1124.3910341645749" yMax="360.3766472343166" yMin="347.42522470657605" />
    <edge0 x1="1134.1849107417786" x2="1134.2188698691566" y1="360.3766472343166" y2="347.4252440504939" />
    <edge1 x1="1134.2188698691566" x2="1135.6617498302542" y1="347.4252440504939" y2="347.42522470657605" />
    <edge2 x1="1135.6617498302542" x2="1135.6276913767967" y1="347.42522470657605" y2="360.37664554957036" />
    <edge3 x1="1135.6276913767967" x2="1134.1849107417786" y1="360.37664554957036" y2="360.3766472343166" />
    <edge4 x1="1134.1849107417786" x2="1124.3910341645749" y1="360.3766472343166" y2="360.3260142547224" />
    <edge5 x1="1124.3910341645749" x2="1124.4236591464041" y1="360.3260142547224" y2="347.63150032034446" />
    <edge6 x1="1124.4236591464041" x2="1134.2188698691566" y1="347.63150032034446" y2="347.4252440504939" />
    <edge7 x1="1124.4236591464041" x2="1125.8379062782237" y1="347.63150032034446" y2="347.6314816357654" />
    <edge8 x1="1125.8379062782237" x2="1125.8051858731671" y1="347.6314816357654" y2="360.32601253572767" />
    <edge9 x1="1125.8051858731671" x2="1124.3910341645749" y1="360.32601253572767" y2="360.3260142547224" />
    <edge10 x1="1125.8051858731671" x2="1135.6276913767967" y1="360.32601253572767" y2="360.37664554957036" />
    <edge11 x1="1125.8379062782237" x2="1135.6617498302542" y1="347.6314816357654" y2="347.42522470657605" />
  </BoundingBox>
</OccludedBoundingBoxes>
