<DynamicBoundingBoxes>
  <BoundingBox class="carla.libcarla.Vehicle" actorId="412">
    <center x="41.859710693359375" y="216.92648315429688" z="0.21710102260112762" />
    <verts>
      <v0 x="43.210472106933594" y="200.00286865234375" z="2.0279603004455566" />
      <v1 x="43.20284652709961" y="200.00274658203125" z="3.618032932281494" />
      <v2 x="42.351890563964844" y="199.89027404785156" z="2.0238354206085205" />
      <v3 x="42.344268798828125" y="199.89013671875" z="3.613908052444458" />
      <v4 x="42.97419357299805" y="201.80455017089844" z="2.0269718170166016" />
      <v5 x="42.96657180786133" y="201.80442810058594" z="3.617044448852539" />
      <v6 x="42.11561584472656" y="201.69195556640625" z="2.0228469371795654" />
      <v7 x="42.10799026489258" y="201.6918182373047" z="3.612919569015503" />
    </verts>
    <shape x="1.8171066045761108" y="0.8659406304359436" z="1.5900908708572388" />
    <word_orientation pitch="0.07668936252593994" yaw="90.08379364013672" roll="-0.0001525854750070721" />
    <relative_orientation pitch="0.10785551369190216" yaw="90.11495979130268" roll="0.031013565690955147" observation_angle="0.1864821910986375" />
    <relative_center x="-177.8619842529297" y="214.13470458984375" z="1.1867778301239014" />
    <Box2d xMin="855.5174260988424" xMax="913.2855504942232" yMin="552.0242961100771" yMax="654.9699068175036" />
    <edge0 x1="858.3863286659789" y1="654.9699068175036" x2="857.9021041304546" y2="553.9571215354908" />
    <edge1 x1="857.9021041304546" y1="553.9571215354908" x2="912.815577575836" y2="553.5930126068178" />
    <edge2 x1="912.815577575836" y1="553.5930126068178" x2="913.2855504942232" y2="653.867038201788" />
    <edge3 x1="913.2855504942232" y1="653.867038201788" x2="858.3863286659789" y2="654.9699068175036" />
    <edge4 x1="858.3863286659789" y1="654.9699068175036" x2="855.9504583057957" y2="642.5899061135951" />
    <edge5 x1="855.9504583057957" y1="642.5899061135951" x2="855.5174260988424" y2="552.3392688228342" />
    <edge6 x1="855.5174260988424" y1="552.3392688228342" x2="857.9021041304546" y2="553.9571215354908" />
    <edge7 x1="855.5174260988424" y1="552.3392688228342" x2="904.6330271627213" y2="552.0242961100771" />
    <edge8 x1="904.6330271627213" y1="552.0242961100771" x2="905.0546184651845" y2="641.6847404245109" />
    <edge9 x1="905.0546184651845" y1="641.6847404245109" x2="855.9504583057957" y2="642.5899061135951" />
    <edge10 x1="905.0546184651845" y1="641.6847404245109" x2="913.2855504942232" y2="653.867038201788" />
    <edge11 x1="904.6330271627213" y1="552.0242961100771" x2="912.815577575836" y2="553.5930126068178" />
  </BoundingBox>
  <BoundingBox class="carla.libcarla.TrafficLight" actorId="316">
    <center x="56.2599983215332" y="234.1999969482422" z="0.2199999988079071" />
    <verts>
      <v0 x="36.31772232055664" y="196.37547302246094" z="1.9950226545333862" />
      <v1 x="36.308135986328125" y="196.37530517578125" z="3.994999885559082" />
      <v2 x="35.32622528076172" y="196.2454376220703" z="1.990259051322937" />
      <v3 x="35.31663513183594" y="196.24526977539062" z="3.990236282348633" />
      <v4 x="36.05766296386719" y="198.35848999023438" z="1.9939347505569458" />
      <v5 x="36.04807662963867" y="198.3583221435547" z="3.9939117431640625" />
      <v6 x="35.066165924072266" y="198.22845458984375" z="1.9891711473464966" />
      <v7 x="35.056575775146484" y="198.22830200195312" z="3.9891481399536133" />
    </verts>
    <shape x="2.0" y="1.0" z="2.0" />
    <word_orientation pitch="0.0" yaw="-89.99993896484375" roll="0.0" />
    <relative_orientation pitch="0.03116615116596222" yaw="-89.96877281367779" roll="0.03116615116596222" observation_angle="2.9571505967386895" />
    <relative_center x="-196.8611297607422" y="226.16665649414062" z="1.0995590686798096" />
    <Box2d xMin="181.91529927836456" xMax="251.24503548185098" yMin="537.2022344841405" yMax="597.5718349667524" />
    <edge0 x1="251.24503548185098" y1="593.8615779028172" x2="250.95323194373995" y2="537.3700029853253" />
    <edge1 x1="250.95323194373995" y1="537.3700029853253" x2="220.11561741015134" y2="537.4958356067164" />
    <edge2 x1="220.11561741015134" y1="537.4958356067164" x2="220.4095325186329" y2="594.2043652601483" />
    <edge3 x1="220.4095325186329" y1="594.2043652601483" x2="251.24503548185098" y2="593.8615779028172" />
    <edge4 x1="251.24503548185098" y1="593.8615779028172" x2="215.13017526934757" y2="597.1941247676765" />
    <edge5 x1="215.13017526934757" y1="597.1941247676765" x2="214.8190628111823" y2="537.2022344841405" />
    <edge6 x1="214.8190628111823" y1="537.2022344841405" x2="250.95323194373995" y2="537.3700029853253" />
    <edge7 x1="214.8190628111823" y1="537.2022344841405" x2="181.91529927836456" y2="537.3352120493904" />
    <edge8 x1="181.91529927836456" y1="537.3352120493904" x2="182.22880397294736" y2="597.5718349667524" />
    <edge9 x1="182.22880397294736" y1="597.5718349667524" x2="215.13017526934757" y2="597.1941247676765" />
    <edge10 x1="182.22880397294736" y1="597.5718349667524" x2="220.4095325186329" y2="594.2043652601483" />
    <edge11 x1="181.91529927836456" y1="537.3352120493904" x2="220.11561741015134" y2="537.4958356067164" />
  </BoundingBox>
  <BoundingBox class="carla.libcarla.TrafficLight" actorId="317">
    <center x="39.27000045776367" y="227.12998962402344" z="0.2199999988079071" />
    <verts>
      <v0 x="36.474395751953125" y="196.4957275390625" z="1.9957833290100098" />
      <v1 x="36.46480941772461" y="196.49557495117188" z="3.995760440826416" />
      <v2 x="35.4828987121582" y="196.36569213867188" z="1.9910197257995605" />
      <v3 x="35.47330856323242" y="196.36553955078125" z="3.990996837615967" />
      <v4 x="36.21433639526367" y="198.47874450683594" z="1.9946954250335693" />
      <v5 x="36.204750061035156" y="198.4785919189453" z="3.9946725368499756" />
      <v6 x="35.22283935546875" y="198.34872436523438" z="1.9899318218231201" />
      <v7 x="35.21324920654297" y="198.3485565185547" z="3.9899089336395264" />
    </verts>
    <shape x="2.0" y="1.0" z="2.0" />
    <word_orientation pitch="0.0" yaw="179.99989318847656" roll="0.0" />
    <relative_orientation pitch="0.03116615116596222" yaw="180.03105933964252" roll="0.03116615116596222" observation_angle="1.5877037497196176" />
    <relative_center x="-187.64202880859375" y="210.24021911621094" z="1.142479658126831" />
    <Box2d xMin="828.4983753985351" xMax="932.7367217889425" yMin="529.6292625252286" yMax="634.2172413070888" />
    <edge0 x1="829.2631317478755" y1="629.4086976273869" x2="828.784602531178" y2="530.4982283394543" />
    <edge1 x1="828.784602531178" y1="530.4982283394543" x2="828.4983753985351" y2="529.9825599315924" />
    <edge2 x1="828.4983753985351" y1="529.9825599315924" x2="829.0026799306686" y2="634.2172413070888" />
    <edge3 x1="829.0026799306686" y1="634.2172413070888" x2="829.2631317478755" y2="629.4086976273869" />
    <edge4 x1="829.2631317478755" y1="629.4086976273869" x2="927.765167647254" y2="627.7587999843427" />
    <edge5 x1="927.765167647254" y1="627.7587999843427" x2="927.2984128342558" y2="530.1559217729987" />
    <edge6 x1="927.2984128342558" y1="530.1559217729987" x2="828.784602531178" y2="530.4982283394543" />
    <edge7 x1="927.2984128342558" y1="530.1559217729987" x2="932.2454802558287" y2="529.6292625252286" />
    <edge8 x1="932.2454802558287" y1="529.6292625252286" x2="932.7367217889425" y2="632.41282509357" />
    <edge9 x1="932.7367217889425" y1="632.41282509357" x2="927.765167647254" y2="627.7587999843427" />
    <edge10 x1="932.7367217889425" y1="632.41282509357" x2="829.0026799306686" y2="634.2172413070888" />
    <edge11 x1="932.2454802558287" y1="529.6292625252286" x2="828.4983753985351" y2="529.9825599315924" />
  </BoundingBox>
</DynamicBoundingBoxes>
