<OccludedBoundingBoxes>
  <BoundingBox class="TrafficSigns">
    <on_screen on_screen="true" />
    <center x="196.09999084472656" y="260.17999267578125" z="2.2300000190734863" />
    <verts>
      </verts>
    <shape x="0.6821317672729492" y="0.07595250010490417" z="0.6821319460868835" />
    <word_orientation pitch="0.0" yaw="0.00047111508320085704" roll="0.0" />
    <relative_orientation pitch="0.0" yaw="0.00047111508320085704" roll="0.0" />
    <Box2d xMin="-1659.409646955727" xMax="-1553.452590185031" yMin="504.9449290069249" yMax="543.7644314589278" />
    <edge0 x1="-1659.409646955727" y1="543.764431404779" x2="-1659.409646955727" y2="504.9449295111684" />
    <edge1 x1="-1659.409646955727" y1="504.9449295111684" x2="-1655.0887066398025" y2="504.9449290069249" />
    <edge2 x1="-1655.0887066398025" y1="504.9449290069249" x2="-1655.0887066398025" y2="543.7644314589278" />
    <edge3 x1="-1655.0887066398025" y1="543.7644314589278" x2="-1659.409646955727" y2="543.764431404779" />
    <edge4 x1="-1659.409646955727" y1="543.764431404779" x2="-1557.6055976135717" y2="543.6181259530665" />
    <edge5 x1="-1557.6055976135717" y1="543.6181259530665" x2="-1557.6055976135717" y2="506.3073525098101" />
    <edge6 x1="-1557.6055976135717" y1="506.3073525098101" x2="-1659.409646955727" y2="504.9449295111684" />
    <edge7 x1="-1557.6055976135717" y1="506.3073525098101" x2="-1553.452590185031" y2="506.3073520439999" />
    <edge8 x1="-1553.452590185031" y1="506.3073520439999" x2="-1553.452590185031" y2="543.6181260030882" />
    <edge9 x1="-1553.452590185031" y1="543.6181260030882" x2="-1557.6055976135717" y2="543.6181259530665" />
    <edge10 x1="-1553.452590185031" y1="543.6181260030882" x2="-1655.0887066398025" y2="543.7644314589278" />
    <edge11 x1="-1553.452590185031" y1="506.3073520439999" x2="-1655.0887066398025" y2="504.9449290069249" />
  </BoundingBox>
  <BoundingBox class="TrafficSigns">
    <on_screen on_screen="true" />
    <center x="187.14999389648438" y="283.8500061035156" z="2.2300000190734863" />
    <verts>
      </verts>
    <shape x="0.6821317672729492" y="0.07595250010490417" z="0.6821319460868835" />
    <word_orientation pitch="0.0" yaw="179.99986267089844" roll="0.0" />
    <relative_orientation pitch="0.0" yaw="179.99986267089844" roll="0.0" />
    <Box2d xMin="-1750.42197783568" xMax="-1526.990491293883" yMin="465.32529605771464" yMax="548.0190339583675" />
    <edge0 x1="-1526.990491293883" y1="547.3830646407738" x2="-1526.990491293883" y2="471.2475581100068" />
    <edge1 x1="-1526.990491293883" y1="471.2475581100068" x2="-1535.4650232842869" y2="471.24756004961904" />
    <edge2 x1="-1535.4650232842869" y1="471.24756004961904" x2="-1535.4650232842869" y2="547.3830644324862" />
    <edge3 x1="-1535.4650232842869" y1="547.3830644324862" x2="-1526.990491293883" y2="547.3830646407738" />
    <edge4 x1="-1526.990491293883" y1="547.3830646407738" x2="-1741.2174652803576" y2="548.0190339583675" />
    <edge5 x1="-1741.2174652803576" y1="548.0190339583675" x2="-1741.2174652803576" y2="465.32529605771464" />
    <edge6 x1="-1741.2174652803576" y1="465.32529605771464" x2="-1526.990491293883" y2="471.2475581100068" />
    <edge7 x1="-1741.2174652803576" y1="465.32529605771464" x2="-1750.42197783568" y2="465.32529834587086" />
    <edge8 x1="-1750.42197783568" y1="465.32529834587086" x2="-1750.42197783568" y2="548.0190337126511" />
    <edge9 x1="-1750.42197783568" y1="548.0190337126511" x2="-1741.2174652803576" y2="548.0190339583675" />
    <edge10 x1="-1750.42197783568" y1="548.0190337126511" x2="-1535.4650232842869" y2="547.3830644324862" />
    <edge11 x1="-1750.42197783568" y1="465.32529834587086" x2="-1535.4650232842869" y2="471.24756004961904" />
  </BoundingBox>
</OccludedBoundingBoxes>
