<OccludedBoundingBoxes>
  <BoundingBox class="TrafficLight">
    <on_screen on_screen="false" />
    <center x="187.15576171875" y="225.91940307617188" z="2.724909543991089" />
    <verts>
      </verts>
    <shape x="0.27714842557907104" y="0.45076170563697815" z="1.221373438835144" />
    <word_orientation pitch="0.0" yaw="-179.99937438964844" roll="0.0" />
    <relative_orientation pitch="-0.0005327546969056129" yaw="-179.99990714434534" roll="-0.0005327546969056129" />
    <Box2d xMin="829.1062591893622" xMax="835.5626787669578" yMin="514.287797850633" yMax="537.9956583397483" />
    <edge0 x1="834.4942621872348" y1="537.9788661578297" x2="834.4873410795585" y2="514.287797850633" />
    <edge1 x1="834.4873410795585" y1="514.287797850633" x2="835.5558283627679" y2="514.5171418043295" />
    <edge2 x1="835.5558283627679" y1="514.5171418043295" x2="835.5626787669578" y2="537.9943915469371" />
    <edge3 x1="835.5626787669578" y1="537.9943915469371" x2="834.4942621872348" y2="537.9788661578297" />
    <edge4 x1="834.4942621872348" y1="537.9788661578297" x2="829.1132224567456" y2="537.9801438449672" />
    <edge5 x1="829.1132224567456" y1="537.9801438449672" x2="829.1062591893622" y2="514.2880938240143" />
    <edge6 x1="829.1062591893622" y1="514.2880938240143" x2="834.4873410795585" y2="514.287797850633" />
    <edge7 x1="829.1062591893622" y1="514.2880938240143" x2="830.2233580964181" y2="514.5174445242652" />
    <edge8 x1="830.2233580964181" y1="514.5174445242652" x2="830.2302499020386" y2="537.9956583397483" />
    <edge9 x1="830.2302499020386" y1="537.9956583397483" x2="829.1132224567456" y2="537.9801438449672" />
    <edge10 x1="830.2302499020386" y1="537.9956583397483" x2="835.5626787669578" y2="537.9943915469371" />
    <edge11 x1="830.2233580964181" y1="514.5174445242652" x2="835.5558283627679" y2="514.5171418043295" />
  </BoundingBox>
  <BoundingBox class="TrafficLight">
    <on_screen on_screen="false" />
    <center x="178.95944213867188" y="243.53421020507812" z="2.724909543991089" />
    <verts>
      </verts>
    <shape x="0.45076170563697815" y="0.2771874964237213" z="1.221373438835144" />
    <word_orientation pitch="0.0" yaw="90.0000991821289" roll="0.0" />
    <relative_orientation pitch="-0.0005327546969056129" yaw="89.999566427432" roll="-0.0005327546969056129" />
    <Box2d xMin="513.0306917850749" xMax="527.4641994485985" yMin="500.2323834737968" yMax="537.123691150043" />
    <edge0 x1="527.4641994485985" y1="537.1217867643079" x2="527.4499193958713" y2="500.78417602177814" />
    <edge1 x1="527.4499193958713" y1="500.78417602177814" x2="519.1750918263207" y2="500.78375323173395" />
    <edge2 x1="519.1750918263207" y1="500.78375323173395" x2="519.1894715583642" y2="537.123691150043" />
    <edge3 x1="519.1894715583642" y1="537.123691150043" x2="527.4641994485985" y2="537.1217867643079" />
    <edge4 x1="527.4641994485985" y1="537.1217867643079" x2="521.4377075105774" y2="537.0852730754714" />
    <edge5 x1="521.4377075105774" y1="537.0852730754714" x2="521.4231522000414" y2="500.2328480635268" />
    <edge6 x1="521.4231522000414" y1="500.2328480635268" x2="527.4499193958713" y2="500.78417602177814" />
    <edge7 x1="521.4231522000414" y1="500.2328480635268" x2="513.0306917850749" y2="500.2323834737968" />
    <edge8 x1="513.0306917850749" y1="500.2323834737968" x2="513.0453496289962" y2="537.0872020714763" />
    <edge9 x1="513.0453496289962" y1="537.0872020714763" x2="521.4377075105774" y2="537.0852730754714" />
    <edge10 x1="513.0453496289962" y1="537.0872020714763" x2="519.1894715583642" y2="537.123691150043" />
    <edge11 x1="513.0306917850749" y1="500.2323834737968" x2="519.1750918263207" y2="500.78375323173395" />
  </BoundingBox>
  <BoundingBox class="TrafficLight">
    <on_screen on_screen="false" />
    <center x="196.0043182373047" y="251.07061767578125" z="2.724909543991089" />
    <verts>
      </verts>
    <shape x="0.2771874964237213" y="0.45076170563697815" z="1.221373438835144" />
    <word_orientation pitch="0.0" yaw="-0.0003662109375" roll="0.0" />
    <relative_orientation pitch="-0.0005327546969056129" yaw="-0.0008989656344056129" roll="-0.0005327546969056129" />
    <Box2d xMin="1048.2358282923904" xMax="1060.9027844199818" yMin="488.0826227396376" yMax="536.1908411115179" />
    <edge0 x1="1048.2462973886709" y1="536.1908411115179" x2="1048.2358282923904" y2="489.01867862804613" />
    <edge1 x1="1048.2358282923904" y1="489.01867862804613" x2="1049.997709326179" y2="488.0826227396376" />
    <edge2 x1="1049.997709326179" y1="488.0826227396376" x2="1050.0083439797795" y2="536.126045395317" />
    <edge3 x1="1050.0083439797795" y1="536.126045395317" x2="1048.2462973886709" y2="536.1908411115179" />
    <edge4 x1="1048.2462973886709" y1="536.1908411115179" x2="1058.9433349892506" y2="536.1884466662715" />
    <edge5 x1="1058.9433349892506" y1="536.1884466662715" x2="1058.93303248411" y2="489.0202054289708" />
    <edge6 x1="1058.93303248411" y1="489.0202054289708" x2="1048.2358282923904" y2="489.01867862804613" />
    <edge7 x1="1058.93303248411" y1="489.0202054289708" x2="1060.8923225628655" y2="488.08425698645806" />
    <edge8 x1="1060.8923225628655" y1="488.08425698645806" x2="1060.9027844199818" y2="536.1236122153173" />
    <edge9 x1="1060.9027844199818" y1="536.1236122153173" x2="1058.9433349892506" y2="536.1884466662715" />
    <edge10 x1="1060.9027844199818" y1="536.1236122153173" x2="1050.0083439797795" y2="536.126045395317" />
    <edge11 x1="1060.8923225628655" y1="488.08425698645806" x2="1049.997709326179" y2="488.0826227396376" />
  </BoundingBox>
  <BoundingBox class="TrafficSigns">
    <on_screen on_screen="false" />
    <center x="187.45999145507812" y="254.0399932861328" z="2.2300000190734863" />
    <verts>
      </verts>
    <shape x="0.6821317672729492" y="0.07595250010490417" z="0.6821319460868835" />
    <word_orientation pitch="0.0" yaw="179.9990997314453" roll="0.0" />
    <relative_orientation pitch="-0.0005327546969056129" yaw="179.9985669767484" roll="-0.0005327546969056129" />
    <Box2d xMin="673.3313969950808" xMax="704.6505000210567" yMin="515.4068504063307" yMax="545.7839017435572" />
    <edge0 x1="703.7764473871595" y1="545.774842543719" x2="703.766271844738" y2="515.4068504063307" />
    <edge1 x1="703.766271844738" y1="515.4068504063307" x2="704.640368875586" y2="515.4921003199323" />
    <edge2 x1="704.640368875586" y1="515.4921003199323" x2="704.6505000210567" y2="545.7535208698098" />
    <edge3 x1="704.6505000210567" y1="545.7535208698098" x2="703.7764473871595" y2="545.774842543719" />
    <edge4 x1="703.7764473871595" y1="545.774842543719" x2="673.3418785795099" y2="545.7839017435572" />
    <edge5 x1="673.3418785795099" y1="545.7839017435572" x2="673.3313969950808" y2="515.4087251819021" />
    <edge6 x1="673.3313969950808" y1="515.4087251819021" x2="703.766271844738" y2="515.4068504063307" />
    <edge7 x1="673.3313969950808" y1="515.4087251819021" x2="674.3125317893133" y2="515.4939886125" />
    <edge8 x1="674.3125317893133" y1="515.4939886125" x2="674.3229668279572" y2="545.7625432440361" />
    <edge9 x1="674.3229668279572" y1="545.7625432440361" x2="673.3418785795099" y2="545.7839017435572" />
    <edge10 x1="674.3229668279572" y1="545.7625432440361" x2="704.6505000210567" y2="545.7535208698098" />
    <edge11 x1="674.3125317893133" y1="515.4939886125" x2="704.640368875586" y2="515.4921003199323" />
  </BoundingBox>
  <BoundingBox class="TrafficSigns">
    <on_screen on_screen="false" />
    <center x="196.09999084472656" y="260.17999267578125" z="2.2300000190734863" />
    <verts>
      </verts>
    <shape x="0.6821317672729492" y="0.07595250010490417" z="0.6821319460868835" />
    <word_orientation pitch="0.0" yaw="0.00047111508320085704" roll="0.0" />
    <relative_orientation pitch="-0.0005327546969056129" yaw="-6.16396137047559e-05" roll="-0.0005327546969056129" />
    <Box2d xMin="1098.6586629373974" xMax="1141.6148964593476" yMin="505.74305723772403" yMax="548.0370507298003" />
    <edge0 x1="1098.6673066373498" y1="547.9963635549844" x2="1098.6586629373974" y2="505.9087567606481" />
    <edge1 x1="1098.6586629373974" y1="505.9087567606481" x2="1099.373706286906" y2="505.74305723772403" />
    <edge2 x1="1099.373706286906" y1="505.74305723772403" x2="1099.3823824400686" y2="548.0370507298003" />
    <edge3 x1="1099.3823824400686" y1="548.0370507298003" x2="1098.6673066373498" y2="547.9963635549844" />
    <edge4 x1="1098.6673066373498" y1="547.9963635549844" x2="1140.694037210398" y2="547.9830954926805" />
    <edge5 x1="1140.694037210398" y1="547.9830954926805" x2="1140.6859771037584" y2="505.9092393229233" />
    <edge6 x1="1140.6859771037584" y1="505.9092393229233" x2="1098.6586629373974" y2="505.9087567606481" />
    <edge7 x1="1140.6859771037584" y1="505.9092393229233" x2="1141.6068096286826" y2="505.74359656810867" />
    <edge8 x1="1141.6068096286826" y1="505.74359656810867" x2="1141.6148964593476" y2="548.0237042682093" />
    <edge9 x1="1141.6148964593476" y1="548.0237042682093" x2="1140.694037210398" y2="547.9830954926805" />
    <edge10 x1="1141.6148964593476" y1="548.0237042682093" x2="1099.3823824400686" y2="548.0370507298003" />
    <edge11 x1="1141.6068096286826" y1="505.74359656810867" x2="1099.373706286906" y2="505.74305723772403" />
  </BoundingBox>
</OccludedBoundingBoxes>
