<DynamicBoundingBoxes>
  <BoundingBox class="Car" actorId="610">
    <center x="45.85699462890625" y="268.8299560546875" z="0.3613555133342743" />
    <verts>
      <v0 x="43.826297760009766" y="296.1197204589844" z="1.8601970672607422" />
      <v1 x="43.82851028442383" y="296.125244140625" z="3.510838031768799" />
      <v2 x="45.960472106933594" y="296.3925476074219" z="1.8564223051071167" />
      <v3 x="45.96268844604492" y="296.3980407714844" z="3.507063388824463" />
      <v4 x="44.46369552612305" y="291.133544921875" z="1.876018762588501" />
      <v5 x="44.465911865234375" y="291.1390686035156" z="3.5266597270965576" />
      <v6 x="46.59787368774414" y="291.4063720703125" z="1.8722440004348755" />
      <v7 x="46.6000862121582" y="291.411865234375" z="3.5228848457336426" />
    </verts>
    <shape x="5.0267767906188965" y="2.1515462398529053" z="1.6506516933441162" />
    <word_orientation pitch="-9.56226431299001e-05" yaw="-89.82958221435547" roll="4.972068563802168e-05" />
    <relative_orientation pitch="-0.18043309639324434" yaw="-90.00991968810558" roll="-0.18028775306447642" observation_angle="2.957662777700208" />
    <relative_center x="317.6880187988281" y="282.3647766113281" z="2.058788299560547" />
    <Box2d xMin="818.0972740312247" xMax="911.1788566640412" yMin="549.1222444764387" yMax="622.1245844491341" />
    <edge0 x1="818.1893761206411" y1="622.1245844491341" x2="818.0972740312247" y2="550.6814881230105" />
    <edge1 x1="818.0972740312247" y1="550.6814881230105" x2="911.0664932218099" y2="550.4305081101083" />
    <edge2 x1="911.0664932218099" y1="550.4305081101083" x2="911.1788566640412" y2="621.0254843462506" />
    <edge3 x1="911.1788566640412" y1="621.0254843462506" x2="818.1893761206411" y2="622.1245844491341" />
    <edge4 x1="818.1893761206411" y1="622.1245844491341" x2="822.2277153444898" y2="607.640697592649" />
    <edge5 x1="822.2277153444898" y1="607.640697592649" x2="822.1518833890575" y2="549.3143328720777" />
    <edge6 x1="822.1518833890575" y1="549.3143328720777" x2="818.0972740312247" y2="550.6814881230105" />
    <edge7 x1="822.1518833890575" y1="549.3143328720777" x2="898.181979625081" y2="549.1222444764387" />
    <edge8 x1="898.181979625081" y1="549.1222444764387" x2="898.2716075011307" y2="606.8820248753475" />
    <edge9 x1="898.2716075011307" y1="606.8820248753475" x2="822.2277153444898" y2="607.640697592649" />
    <edge10 x1="898.2716075011307" y1="606.8820248753475" x2="911.1788566640412" y2="621.0254843462506" />
    <edge11 x1="898.181979625081" y1="549.1222444764387" x2="911.0664932218099" y2="550.4305081101083" />
  </BoundingBox>
  <BoundingBox class="Walker" actorId="612">
    <center x="36.50077438354492" y="267.2024230957031" z="1.2745897769927979" />
    <verts>
      <v0 x="45.00185775756836" y="293.92291259765625" z="1.094494342803955" />
      <v1 x="45.00435256958008" y="293.92913818359375" z="2.954482316970825" />
      <v2 x="45.374183654785156" y="293.97052001953125" z="1.0938358306884766" />
      <v3 x="45.376678466796875" y="293.97674560546875" z="2.9538238048553467" />
      <v4 x="45.04945373535156" y="293.55059814453125" z="1.0956757068634033" />
      <v5 x="45.05194854736328" y="293.55682373046875" z="2.9556636810302734" />
      <v6 x="45.42177963256836" y="293.59820556640625" z="1.0950171947479248" />
      <v7 x="45.42427444458008" y="293.60443115234375" z="2.955005168914795" />
    </verts>
    <shape x="0.3753577768802643" y="0.3753577768802643" z="1.8600000143051147" />
    <word_orientation pitch="0.0" yaw="90.07305908203125" roll="0.0" />
    <relative_orientation pitch="-0.18033747375011444" yaw="89.89272160828114" roll="-0.18033747375011444" observation_angle="0.181691399647738" />
    <relative_center x="314.88848876953125" y="291.442138671875" z="2.9454236030578613" />
    <Box2d xMin="493.17815783484315" xMax="513.1611594384761" yMin="536.9301677284843" yMax="608.2897376414819" />
    <edge0 x1="513.1611594384761" y1="607.1922053113436" x2="513.1408542907978" y2="537.0224101573473" />
    <edge1 x1="513.1408542907978" y1="537.0224101573473" x2="498.24046961132177" y2="537.0359735291325" />
    <edge2 x1="498.24046961132177" y1="537.0359735291325" x2="498.2573780210353" y2="607.3359249811051" />
    <edge3 x1="498.2573780210353" y1="607.3359249811051" x2="513.1611594384761" y2="607.1922053113436" />
    <edge4 x1="513.1611594384761" y1="607.1922053113436" x2="508.3287768379855" y2="608.1420913579816" />
    <edge5 x1="508.3287768379855" y1="608.1420913579816" x2="508.30929819761207" y2="536.9301677284843" />
    <edge6 x1="508.30929819761207" y1="536.9301677284843" x2="513.1408542907978" y2="537.0224101573473" />
    <edge7 x1="508.30929819761207" y1="536.9301677284843" x2="493.17815783484315" y2="536.943759273756" />
    <edge8 x1="493.17815783484315" y1="536.943759273756" x2="493.1941336602034" y2="608.2897376414819" />
    <edge9 x1="493.1941336602034" y1="608.2897376414819" x2="508.3287768379855" y2="608.1420913579816" />
    <edge10 x1="493.1941336602034" y1="608.2897376414819" x2="498.2573780210353" y2="607.3359249811051" />
    <edge11 x1="493.17815783484315" y1="536.943759273756" x2="498.24046961132177" y2="537.0359735291325" />
  </BoundingBox>
  <BoundingBox class="Bicycle" actorId="593">
    <center x="45.820526123046875" y="280.8788757324219" z="0.2027842253446579" />
    <verts>
      <v0 x="44.92417526245117" y="294.55487060546875" z="2.03593111038208" />
      <v1 x="44.9259147644043" y="294.5592041015625" z="3.3318753242492676" />
      <v2 x="44.92417526245117" y="294.55487060546875" z="2.03593111038208" />
      <v3 x="44.9259147644043" y="294.5592041015625" z="3.3318753242492676" />
      <v4 x="44.92417526245117" y="294.55487060546875" z="2.03593111038208" />
      <v5 x="44.9259147644043" y="294.5592041015625" z="3.3318753242492676" />
      <v6 x="44.92417526245117" y="294.55487060546875" z="2.03593111038208" />
      <v7 x="44.9259147644043" y="294.5592041015625" z="3.3318753242492676" />
    </verts>
    <shape x="0.0" y="0.0" z="1.2959526777267456" />
    <word_orientation pitch="-0.3059992790222168" yaw="-89.57586669921875" roll="-0.0077209449373185635" />
    <relative_orientation pitch="-0.48633675277233124" yaw="-89.75620417296886" roll="-0.188058418687433" observation_angle="2.9515775217532947" />
    <relative_center x="329.6348571777344" y="283.9281921386719" z="1.8789639472961426" />
    <Box2d xMin="870.739863876783" xMax="870.9204647536266" yMin="583.7512878792731" yMax="687.3392946169903" />
    <edge0 x1="870.9204647536266" y1="687.3392946169903" x2="870.739863876783" y2="583.7512878792731" />
    <edge1 x1="870.739863876783" y1="583.7512878792731" x2="870.739863876783" y2="583.7512878792731" />
    <edge2 x1="870.739863876783" y1="583.7512878792731" x2="870.9204647536266" y2="687.3392946169903" />
    <edge3 x1="870.9204647536266" y1="687.3392946169903" x2="870.9204647536266" y2="687.3392946169903" />
    <edge4 x1="870.9204647536266" y1="687.3392946169903" x2="870.9204647536266" y2="687.3392946169903" />
    <edge5 x1="870.9204647536266" y1="687.3392946169903" x2="870.739863876783" y2="583.7512878792731" />
    <edge6 x1="870.739863876783" y1="583.7512878792731" x2="870.739863876783" y2="583.7512878792731" />
    <edge7 x1="870.739863876783" y1="583.7512878792731" x2="870.739863876783" y2="583.7512878792731" />
    <edge8 x1="870.739863876783" y1="583.7512878792731" x2="870.9204647536266" y2="687.3392946169903" />
    <edge9 x1="870.9204647536266" y1="687.3392946169903" x2="870.9204647536266" y2="687.3392946169903" />
    <edge10 x1="870.9204647536266" y1="687.3392946169903" x2="870.9204647536266" y2="687.3392946169903" />
    <edge11 x1="870.739863876783" y1="583.7512878792731" x2="870.739863876783" y2="583.7512878792731" />
  </BoundingBox>
  <BoundingBox class="Car" actorId="595">
    <center x="41.8590087890625" y="283.3755187988281" z="0.2585979104042053" />
    <verts>
      <v0 x="44.04457473754883" y="295.62420654296875" z="1.9734563827514648" />
      <v1 x="44.0467414855957" y="295.6296081542969" z="3.590555429458618" />
      <v2 x="45.8804817199707" y="295.85888671875" z="1.9702091217041016" />
      <v3 x="45.88264846801758" y="295.8642883300781" z="3.587308168411255" />
      <v4 x="44.55021667480469" y="291.6687316894531" z="1.9860074520111084" />
      <v5 x="44.55238342285156" y="291.67413330078125" z="3.6031064987182617" />
      <v6 x="46.38612365722656" y="291.9034118652344" z="1.9827603101730347" />
      <v7 x="46.38829040527344" y="291.9088134765625" z="3.5998592376708984" />
    </verts>
    <shape x="3.987684965133667" y="1.8508483171463013" z="1.6171095371246338" />
    <word_orientation pitch="-0.00015709434228483588" yaw="89.9131088256836" roll="0.0" />
    <relative_orientation pitch="-0.18049456809239928" yaw="89.73277135193348" roll="-0.18033747375011444" observation_angle="0.17758050851659712" />
    <relative_center x="331.60906982421875" y="288.1744689941406" z="1.9179283380508423" />
    <Box2d xMin="305.0981899381204" xMax="640.6676065169097" yMin="559.2699352218642" yMax="767.9497834411973" />
    <edge0 x1="640.6676065169097" y1="688.9810292650038" x2="640.5758828500256" y2="559.2699352218642" />
    <edge1 x1="640.5758828500256" y1="559.2699352218642" x2="483.9737071188947" y2="559.8621102214179" />
    <edge2 x1="483.9737071188947" y1="559.8621102214179" x2="483.99934443677614" y2="692.1991183868339" />
    <edge3 x1="483.99934443677614" y1="692.1991183868339" x2="640.6676065169097" y2="688.9810292650038" />
    <edge4 x1="640.6676065169097" y1="688.9810292650038" x2="544.3761416141544" y2="760.8991298951978" />
    <edge5 x1="544.3761416141544" y1="760.8991298951978" x2="544.3003002503182" y2="567.1765184768519" />
    <edge6 x1="544.3003002503182" y1="567.1765184768519" x2="640.5758828500256" y2="559.2699352218642" />
    <edge7 x1="544.3003002503182" y1="567.1765184768519" x2="305.17653535576926" y2="568.3109086162696" />
    <edge8 x1="305.17653535576926" y1="568.3109086162696" x2="305.0981899381204" y2="767.9497834411973" />
    <edge9 x1="305.0981899381204" y1="767.9497834411973" x2="544.3761416141544" y2="760.8991298951978" />
    <edge10 x1="305.0981899381204" y1="767.9497834411973" x2="483.99934443677614" y2="692.1991183868339" />
    <edge11 x1="305.17653535576926" y1="568.3109086162696" x2="483.9737071188947" y2="559.8621102214179" />
  </BoundingBox>
  <BoundingBox class="Car" actorId="607">
    <center x="45.85625457763672" y="259.4400634765625" z="0.18978993594646454" />
    <verts>
      <v0 x="43.890350341796875" y="296.07818603515625" z="2.0403943061828613" />
      <v1 x="43.892417907714844" y="296.0833435058594" z="3.582502603530884" />
      <v2 x="45.912296295166016" y="296.3366394042969" z="2.036818027496338" />
      <v3 x="45.914363861083984" y="296.341796875" z="3.5789263248443604" />
      <v4 x="44.521087646484375" y="291.14410400390625" z="2.0560507774353027" />
      <v5 x="44.523155212402344" y="291.1492614746094" z="3.598158836364746" />
      <v6 x="46.543033599853516" y="291.402587890625" z="2.0524744987487793" />
      <v7 x="46.545101165771484" y="291.4077453613281" z="3.5945825576782227" />
    </verts>
    <shape x="4.974244117736816" y="2.0384011268615723" z="1.5421181917190552" />
    <word_orientation pitch="-0.047852303832769394" yaw="-90.07311248779297" roll="-0.00012206965038785711" />
    <relative_orientation pitch="-0.22818977758288383" yaw="-90.25344996154308" roll="-0.1804595434005023" observation_angle="2.9636882663968356" />
    <relative_center x="308.37359619140625" y="281.1743469238281" z="1.9036955833435059" />
    <Box2d xMin="825.8782659190565" xMax="888.0512357843833" yMin="550.3003585794288" yMax="598.3734711486304" />
    <edge0 x1="825.9397233407325" y1="598.3734711486304" x2="825.8782659190565" y2="551.4461785532425" />
    <edge1 x1="825.8782659190565" y1="551.4461785532425" x2="887.9784312844579" y2="551.269904865405" />
    <edge2 x1="887.9784312844579" y1="551.269904865405" x2="888.0512357843833" y2="597.8120037916914" />
    <edge3 x1="888.0512357843833" y1="597.8120037916914" x2="825.9397233407325" y2="598.3734711486304" />
    <edge4 x1="825.9397233407325" y1="598.3734711486304" x2="827.3056173450068" y2="591.0272534866103" />
    <edge5 x1="827.3056173450068" y1="591.0272534866103" x2="827.2522387062563" y2="550.4458664628329" />
    <edge6 x1="827.2522387062563" y1="550.4458664628329" x2="825.8782659190565" y2="551.4461785532425" />
    <edge7 x1="827.2522387062563" y1="550.4458664628329" x2="881.006217061147" y2="550.3003585794288" />
    <edge8 x1="881.006217061147" y1="550.3003585794288" x2="881.0680843400692" y2="590.5933690211012" />
    <edge9 x1="881.0680843400692" y1="590.5933690211012" x2="827.3056173450068" y2="591.0272534866103" />
    <edge10 x1="881.0680843400692" y1="590.5933690211012" x2="888.0512357843833" y2="597.8120037916914" />
    <edge11 x1="881.006217061147" y1="550.3003585794288" x2="887.9784312844579" y2="551.269904865405" />
  </BoundingBox>
  <BoundingBox class="TrafficLight" actorId="489">
    <verts>
      <v0 x="301.0884094238281" y="277.90081787109375" z="3.848860263824463" />
      <v1 x="301.0900573730469" y="277.9048767089844" z="5.070225715637207" />
      <v2 x="301.5355529785156" y="277.95794677734375" z="3.848069429397583" />
      <v3 x="301.5372009277344" y="277.9620361328125" z="5.069435119628906" />
      <v4 x="301.1235656738281" y="277.6258850097656" z="3.8497326374053955" />
      <v5 x="301.1252136230469" y="277.62994384765625" z="5.071098327636719" />
      <v6 x="301.5707092285156" y="277.68304443359375" z="3.8489418029785156" />
      <v7 x="301.5723571777344" y="277.6871032714844" z="5.070307731628418" />
    </verts>
    <on_screen on_screen="false" />
    <center x="48.32429885864258" y="252.0205841064453" z="2.724909543991089" />
    <shape x="0.2771679759025574" y="0.45076170563697815" z="1.221373438835144" />
    <word_orientation pitch="0.0" yaw="0.0" roll="0.0" />
    <relative_orientation pitch="-0.17894411087036133" yaw="-0.17894411087036133" roll="-0.17894411087036133" />
    <Box2d xMin="905.7263268905506" xMax="912.8977205046097" yMin="512.8383933250724" yMax="541.0719581015215" />
    <edge0 x1="905.770331377904" y1="541.0719581015215" x2="905.7263268905506" y2="513.161936280469" />
    <edge1 x1="905.7263268905506" y1="513.161936280469" x2="906.4626125921938" y2="512.8383933250724" />
    <edge2 x1="906.4626125921938" y1="512.8383933250724" x2="906.5071586247152" y2="541.0486657844065" />
    <edge3 x1="906.5071586247152" y1="541.0486657844065" x2="905.770331377904" y2="541.0719581015215" />
    <edge4 x1="905.770331377904" y1="541.0719581015215" x2="912.0935426483998" y2="541.0625736278694" />
    <edge5 x1="912.0935426483998" y1="541.0625736278694" x2="912.0489968110429" y2="513.1758821210972" />
    <edge6 x1="912.0489968110429" y1="513.1758821210972" x2="905.7263268905506" y2="513.161936280469" />
    <edge7 x1="912.0489968110429" y1="513.1758821210972" x2="912.8526215366873" y2="512.8527624170326" />
    <edge8 x1="912.8526215366873" y1="512.8527624170326" x2="912.8977205046097" y2="541.039200110341" />
    <edge9 x1="912.8977205046097" y1="541.039200110341" x2="912.0935426483998" y2="541.0625736278694" />
    <edge10 x1="912.8977205046097" y1="541.039200110341" x2="906.5071586247152" y2="541.0486657844065" />
    <edge11 x1="912.8526215366873" y1="512.8527624170326" x2="906.4626125921938" y2="512.8383933250724" />
  </BoundingBox>
</DynamicBoundingBoxes>
