<DynamicBoundingBoxes>
  <BoundingBox class="carla.libcarla.Vehicle" actorId="423">
    <center x="193.72149658203125" y="259.17474365234375" z="0.1650780439376831" />
    <verts>
      <v0 x="190.7286834716797" y="298.6825866699219" z="2.041778802871704" />
      <v1 x="190.74435424804688" y="298.68768310546875" z="3.5720715522766113" />
      <v2 x="191.50735473632812" y="299.0612487792969" z="2.0325427055358887" />
      <v3 x="191.5230255126953" y="299.0663757324219" z="3.562835693359375" />
      <v4 x="191.68678283691406" y="296.7124328613281" z="2.0385372638702393" />
      <v5 x="191.70245361328125" y="296.717529296875" z="3.5688300132751465" />
      <v6 x="192.4654541015625" y="297.0910949707031" z="2.029301166534424" />
      <v7 x="192.4811248779297" y="297.0962219238281" z="3.55959415435791" />
    </verts>
    <shape x="2.1907684803009033" y="0.8659172654151917" z="1.530381441116333" />
    <word_orientation pitch="0.1291930228471756" yaw="-90.32426452636719" roll="-0.0011291451519355178" />
    <relative_orientation pitch="0.21396932750940323" yaw="-90.23948822170496" roll="0.08364715951029211" observation_angle="2.520293458463578" />
    <relative_center x="509.38006591796875" y="237.01690673828125" z="-0.8599269390106201" />
    <Box2d xMin="542.5005820723396" xMax="572.0272370135567" yMin="551.0597347998603" yMax="594.480141616471" />
    <edge0 x1="546.1654569400391" y1="594.480141616471" x2="545.6897546114025" y2="551.987980800988" />
    <edge1 x1="545.6897546114025" y1="551.987980800988" x2="571.5607196681024" y2="551.613012065274" />
    <edge2 x1="571.5607196681024" y1="551.613012065274" x2="572.0272370135567" y2="593.6395113007547" />
    <edge3 x1="572.0272370135567" y1="593.6395113007547" x2="546.1654569400391" y2="594.480141616471" />
    <edge4 x1="546.1654569400391" y1="594.480141616471" x2="542.9516092312198" y2="591.6160053357074" />
    <edge5 x1="542.9516092312198" y1="591.6160053357074" x2="542.5005820723396" y2="551.4087291765236" />
    <edge6 x1="542.5005820723396" y1="551.4087291765236" x2="545.6897546114025" y2="551.987980800988" />
    <edge7 x1="542.5005820723396" y1="551.4087291765236" x2="567.0277603831066" y2="551.0597347998603" />
    <edge8 x1="567.0277603831066" y1="551.0597347998603" x2="567.4705385919328" y2="590.8498660944331" />
    <edge9 x1="567.4705385919328" y1="590.8498660944331" x2="542.9516092312198" y2="591.6160053357074" />
    <edge10 x1="567.4705385919328" y1="590.8498660944331" x2="572.0272370135567" y2="593.6395113007547" />
    <edge11 x1="567.0277603831066" y1="551.0597347998603" x2="571.5607196681024" y2="551.613012065274" />
  </BoundingBox>
  <BoundingBox class="carla.libcarla.TrafficSign" actorId="336">
    <center x="196.09999084472656" y="260.1300048828125" z="0.35999998450279236" />
    <verts>
      <v0 x="189.93466186523438" y="300.57830810546875" z="2.235680341720581" />
      <v1 x="189.94895935058594" y="300.58294677734375" z="3.632521152496338" />
      <v2 x="190.5101776123047" y="300.8581848144531" z="2.228853940963745" />
      <v3 x="190.52447509765625" y="300.86285400390625" z="3.625694751739502" />
      <v4 x="190.85108947753906" y="298.6938171386719" z="2.2325799465179443" />
      <v5 x="190.8654022216797" y="298.698486328125" z="3.629420757293701" />
      <v6 x="191.42660522460938" y="298.9737243652344" z="2.2257533073425293" />
      <v7 x="191.44090270996094" y="298.9783630371094" z="3.6225943565368652" />
    </verts>
    <shape x="2.0954959392547607" y="0.6399999856948853" z="1.3969217538833618" />
    <word_orientation pitch="0.0" yaw="0.00047111508320085704" roll="0.0" />
    <relative_orientation pitch="0.08477630466222763" yaw="0.08524741974542849" roll="0.08477630466222763" observation_angle="1.3783421722151346" />
    <relative_center x="511.28131103515625" y="235.2963409423828" z="-0.6787245273590088" />
    <Box2d xMin="534.7088251276961" xMax="598.3227765032625" yMin="544.2758800272752" yMax="584.1421345470349" />
    <edge0 x1="535.1446528312068" y1="583.471644984969" x2="534.7088251276961" y2="544.9796714070629" />
    <edge1 x1="534.7088251276961" y1="544.9796714070629" x2="535.4068713478354" y2="545.0035345609243" />
    <edge2 x1="535.4068713478354" y1="545.0035345609243" x2="535.849978423063" y2="584.1421345470349" />
    <edge3 x1="535.849978423063" y1="584.1421345470349" x2="535.1446528312068" y2="583.471644984969" />
    <edge4 x1="535.1446528312068" y1="583.471644984969" x2="596.6303572869366" y2="581.7813042466125" />
    <edge5 x1="596.6303572869366" y1="581.7813042466125" x2="596.2092556453271" y2="544.2758800272752" />
    <edge6 x1="596.2092556453271" y1="544.2758800272752" x2="534.7088251276961" y2="544.9796714070629" />
    <edge7 x1="596.2092556453271" y1="544.2758800272752" x2="597.8948843385872" y2="544.2876103133343" />
    <edge8 x1="597.8948843385872" y1="544.2876103133343" x2="598.3227765032625" y2="582.4066529195217" />
    <edge9 x1="598.3227765032625" y1="582.4066529195217" x2="596.6303572869366" y2="581.7813042466125" />
    <edge10 x1="598.3227765032625" y1="582.4066529195217" x2="535.849978423063" y2="584.1421345470349" />
    <edge11 x1="597.8948843385872" y1="544.2876103133343" x2="535.4068713478354" y2="545.0035345609243" />
  </BoundingBox>
  <BoundingBox class="carla.libcarla.TrafficSign" actorId="337">
    <center x="187.14999389648438" y="283.8999938964844" z="0.35999998450279236" />
    <verts>
      <v0 x="189.93466186523438" y="300.57830810546875" z="2.235680341720581" />
      <v1 x="189.94895935058594" y="300.58294677734375" z="3.632521152496338" />
      <v2 x="190.5101776123047" y="300.8581848144531" z="2.228853940963745" />
      <v3 x="190.52447509765625" y="300.86285400390625" z="3.625694751739502" />
      <v4 x="190.85108947753906" y="298.6938171386719" z="2.2325799465179443" />
      <v5 x="190.8654022216797" y="298.698486328125" z="3.629420757293701" />
      <v6 x="191.42660522460938" y="298.9737243652344" z="2.2257533073425293" />
      <v7 x="191.44090270996094" y="298.9783630371094" z="3.6225943565368652" />
    </verts>
    <shape x="2.0954959392547607" y="0.6399999856948853" z="1.3969217538833618" />
    <word_orientation pitch="0.0" yaw="179.99986267089844" roll="0.0" />
    <relative_orientation pitch="0.08477630466222763" yaw="180.08463897556067" roll="0.08477630466222763" observation_angle="1.7632420245474734" />
    <relative_center x="528.7421264648438" y="253.74021911621094" z="-0.919020414352417" />
    <Box2d xMin="157.89037692840907" xMax="381.7101772578585" yMin="550.0404298258123" yMax="677.2116634396988" />
    <edge0 x1="376.23937352809446" y1="664.7295339094334" x2="374.91622150132565" y2="550.35863558245" />
    <edge1 x1="374.91622150132565" y1="550.35863558245" x2="380.4498671472068" y2="550.0404298258123" />
    <edge2 x1="380.4498671472068" y1="550.0404298258123" x2="381.7101772578585" y2="659.0598158733718" />
    <edge3 x1="381.7101772578585" y1="659.0598158733718" x2="376.23937352809446" y2="664.7295339094334" />
    <edge4 x1="376.23937352809446" y1="664.7295339094334" x2="159.36722807320575" y2="677.2116634396988" />
    <edge5 x1="159.36722807320575" y1="677.2116634396988" x2="157.89037692840907" y2="553.1433260021116" />
    <edge6 x1="157.89037692840907" y1="553.1433260021116" x2="374.91622150132565" y2="550.35863558245" />
    <edge7 x1="157.89037692840907" y1="553.1433260021116" x2="174.84483017589093" y2="552.6586609307648" />
    <edge8 x1="174.84483017589093" y1="552.6586609307648" x2="176.24393236912442" y2="670.4541115608166" />
    <edge9 x1="176.24393236912442" y1="670.4541115608166" x2="159.36722807320575" y2="677.2116634396988" />
    <edge10 x1="176.24393236912442" y1="670.4541115608166" x2="381.7101772578585" y2="659.0598158733718" />
    <edge11 x1="174.84483017589093" y1="552.6586609307648" x2="380.4498671472068" y2="550.0404298258123" />
  </BoundingBox>
  <BoundingBox class="carla.libcarla.TrafficLight" actorId="312">
    <center x="196.21002197265625" y="250.81002807617188" z="0.2199999988079071" />
    <verts>
      <v0 x="196.5535430908203" y="304.0780944824219" z="1.9546815156936646" />
      <v1 x="196.57403564453125" y="304.0847473144531" z="3.9545655250549316" />
      <v2 x="197.45278930664062" y="304.5154113769531" z="1.9440151453018188" />
      <v3 x="197.4732666015625" y="304.5220947265625" z="3.943899154663086" />
      <v4 x="197.42822265625" y="302.2795104980469" z="1.951722264289856" />
      <v5 x="197.44869995117188" y="302.2861633300781" z="3.951606273651123" />
      <v6 x="198.32745361328125" y="302.7168273925781" z="1.9410558938980103" />
      <v7 x="198.34793090820312" y="302.7234802246094" z="3.9409399032592773" />
    </verts>
    <shape x="2.0" y="1.0" z="2.0" />
    <word_orientation pitch="0.0" yaw="-0.0003662109375" roll="0.0" />
    <relative_orientation pitch="0.08477630466222763" yaw="0.08441009372472763" roll="0.08477630466222763" observation_angle="1.3783538441439878" />
    <relative_center x="502.94708251953125" y="231.12109375" z="-0.7194695472717285" />
    <Box2d xMin="528.6523948284777" xMax="587.923363983147" yMin="537.4398417456521" yMax="591.9721689693043" />
    <edge0 x1="529.249666565082" y1="590.7769105781749" x2="528.6523948284777" y2="538.0692165892856" />
    <edge1 x1="528.6523948284777" y1="538.0692165892856" x2="529.550953371357" y2="537.9302314263794" />
    <edge2 x1="529.550953371357" y1="537.9302314263794" x2="530.1632694764887" y2="591.9721689693043" />
    <edge3 x1="530.1632694764887" y1="591.9721689693043" x2="529.249666565082" y2="590.7769105781749" />
    <edge4 x1="529.249666565082" y1="590.7769105781749" x2="585.6385950546282" y2="589.059155045752" />
    <edge5 x1="585.6385950546282" y1="589.059155045752" x2="585.0598042055869" y2="537.5873916974474" />
    <edge6 x1="585.0598042055869" y1="537.5873916974474" x2="528.6523948284777" y2="538.0692165892856" />
    <edge7 x1="585.0598042055869" y1="537.5873916974474" x2="587.330458391043" y2="537.4398417456521" />
    <edge8 x1="587.330458391043" y1="537.4398417456521" x2="587.923363983147" y2="590.1832547030474" />
    <edge9 x1="587.923363983147" y1="590.1832547030474" x2="585.6385950546282" y2="589.059155045752" />
    <edge10 x1="587.923363983147" y1="590.1832547030474" x2="530.1632694764887" y2="591.9721689693043" />
    <edge11 x1="587.330458391043" y1="537.4398417456521" x2="529.550953371357" y2="537.9302314263794" />
  </BoundingBox>
  <BoundingBox class="carla.libcarla.Vehicle" actorId="413">
    <center x="189.69602966308594" y="282.3039855957031" z="0.2149701714515686" />
    <verts>
      <v0 x="189.27792358398438" y="299.65228271484375" z="2.0439422130584717" />
      <v1 x="189.3031768798828" y="299.6605224609375" z="4.51124382019043" />
      <v2 x="191.6402130126953" y="300.8011474609375" z="2.0159218311309814" />
      <v3 x="191.6654815673828" y="300.8093566894531" z="4.4832234382629395" />
      <v4 x="191.55372619628906" y="294.97247314453125" z="2.0362424850463867" />
      <v5 x="191.57899475097656" y="294.980712890625" z="4.503543853759766" />
      <v6 x="193.916015625" y="296.121337890625" z="2.0082221031188965" />
      <v7 x="193.9412841796875" y="296.1295471191406" z="4.475523948669434" />
    </verts>
    <shape x="5.203838348388672" y="2.6269896030426025" z="2.467444658279419" />
    <word_orientation pitch="0.24741676449775696" yaw="90.14214324951172" roll="0.017351681366562843" />
    <relative_orientation pitch="0.3321930691599846" yaw="90.22691955417395" roll="0.10212798602879047" observation_angle="0.6321242175039576" />
    <relative_center x="528.4188842773438" y="250.75210571289062" z="-1.0507855415344238" />
    <Box2d xMin="157.81134516947859" xMax="455.87399019010206" yMin="484.8089013527724" yMax="715.3901238944759" />
    <edge0 x1="455.87399019010206" y1="652.6069412058062" x2="454.1647960354267" y2="505.49663933068416" />
    <edge1 x1="454.1647960354267" y1="505.49663933068416" x2="263.7663657624381" y2="504.6391254416957" />
    <edge2 x1="263.7663657624381" y1="504.6391254416957" x2="265.53430002329907" y2="662.9919013070923" />
    <edge3 x1="265.53430002329907" y1="662.9919013070923" x2="455.87399019010206" y2="652.6069412058062" />
    <edge4 x1="455.87399019010206" y1="652.6069412058062" x2="439.33963553756666" y2="695.49469417704" />
    <edge5 x1="439.33963553756666" y1="695.49469417704" x2="436.9372789858131" y2="488.00325528346167" />
    <edge6 x1="436.9372789858131" y1="488.00325528346167" x2="454.1647960354267" y2="505.49663933068416" />
    <edge7 x1="436.9372789858131" y1="488.00325528346167" x2="157.81134516947859" y2="484.8089013527724" />
    <edge8 x1="157.81134516947859" y1="484.8089013527724" x2="160.32849772037764" y2="715.3901238944759" />
    <edge9 x1="160.32849772037764" y1="715.3901238944759" x2="439.33963553756666" y2="695.49469417704" />
    <edge10 x1="160.32849772037764" y1="715.3901238944759" x2="265.53430002329907" y2="662.9919013070923" />
    <edge11 x1="157.81134516947859" y1="484.8089013527724" x2="263.7663657624381" y2="504.6391254416957" />
  </BoundingBox>
</DynamicBoundingBoxes>
